mojo/results/concentrators/__init__.py
mojo/results/concentrators/progressconcentratorservice.py
mojo/results/model/__init__.py
mojo/results/model/buildinfo.py
mojo/results/model/forwardinginfo.py
mojo/results/model/jobcontainer.py
mojo/results/model/jobinfo.py
mojo/results/model/pipelineinfo.py
mojo/results/model/progresscode.py
mojo/results/model/progressdelivery.py
mojo/results/model/progressinfo.py
mojo/results/model/progresstype.py
mojo/results/model/renderinfo.py
mojo/results/model/resultcode.py
mojo/results/model/resultcontainer.py
mojo/results/model/resultnode.py
mojo/results/model/resulttype.py
mojo/results/model/taskinggroup.py
mojo/results/model/taskingresult.py
mojo/results/model/testcontainer.py
mojo/results/model/testresult.py
mojo/results/recorders/__init__.py
mojo/results/recorders/jsonresultrecorder.py
mojo/results/recorders/resultrecorder.py
mojo/results/utilities.py
mojo_results-2.0.3.dist-info/LICENSE.txt
mojo_results-2.0.3.dist-info/METADATA
mojo_results-2.0.3.dist-info/WHEEL
mojo_results-2.0.3.dist-info/RECORD
