Metadata-Version: 2.1
Name: mojo-results
Version: 2.0.3
Summary: The Automation Mojo Results Package
License: LICENSE.txt
Keywords: python
Author: Myron W. Walker
Requires-Python: >=3.9,<4.0
Classifier: License :: OSI Approved :: MIT License
Classifier: License :: Other/Proprietary License
Classifier: Operating System :: POSIX
Classifier: Programming Language :: Python :: 3
Classifier: Programming Language :: Python :: 3.9
Classifier: Programming Language :: Python :: 3.10
Classifier: Programming Language :: Python :: 3.11
Classifier: Programming Language :: Python :: 3.12
Requires-Dist: mojo-errors (>=2.0.0,<2.1.0)
Requires-Dist: mojo-xmodules (>=2.0.0,<2.1.0)
